{"The information governing academics is available in other places": [{"sentence": "NNANVNANN", "modifiers0": [], "subject": ["The information"], "modifiers1": [{"m_rel": ["governing"], "m_obj": ["academics"]}], "relation": ["is"], "object": ["available"], "modifiers2": [{"m_rel": ["in"], "m_obj": ["other places"]}]}], "Indraprastha Institute of Information Technology and Delhi (IIIT Delhi) was created as State University by Act of Delhi Government (The IIIT Delhi Act and 2007) empowering Act of Delhi Government (The IIIT Delhi Act and 2007) to do research & development and grant degrees": [{"sentence": "NNANNCNNNVV", "modifiers0": [], "subject": ["Indraprastha Institute"], "modifiers1": [{"m_rel": ["of"], "m_obj": ["Information Technology", "Delhi IIIT Delhi"]}], "relation": ["was created"], "object": [], "modifiers2": []}, {"sentence": "NNANANNNNNNCNANANNNNNNCNNVNCNCNN", "modifiers0": [], "subject": ["State University"], "modifiers1": [{"m_rel": ["by"], "m_obj": ["Act"]}, {"m_rel": ["of"], "m_obj": ["Delhi Government The IIIT Delhi Act", "2007"]}, {"m_rel": ["empowering"], "m_obj": ["Act"]}, {"m_rel": ["of"], "m_obj": ["Delhi Government The IIIT Delhi Act", "2007 to"]}], "relation": ["do"], "object": ["research", "development", "grant degrees"], "modifiers2": []}], " Delhi (IIIT Delhi) was officially established on 10th June and 2008": [{"sentence": "NNNVVAANNCN", "modifiers0": [], "subject": ["Delhi IIIT Delhi"], "modifiers1": [], "relation": ["was officially established on"], "object": ["10th June", "2008"], "modifiers2": []}], " The first class for B.Tech. (CSE) students was held on 8th September and 2008": [{"sentence": "NNNANNNVVANNCN", "modifiers0": [], "subject": ["The first class"], "modifiers1": [{"m_rel": ["for"], "m_obj": ["B.Tech CSE students"]}], "relation": ["was held on"], "object": ["8th September", "2008"], "modifiers2": []}], " The institute began with 60 B.Tech. students in 2008": [{"sentence": "NNVANNNAN", "modifiers0": [], "subject": ["The institute"], "modifiers1": [], "relation": ["began with"], "object": ["60 B.Tech students"], "modifiers2": [{"m_rel": ["in"], "m_obj": ["2008"]}]}], "Campus is spread over 25 acres of lush green land in South Delhi in Okhla Phase-III and near Nehru Place": [{"sentence": "NVVANNANNNANNANNNCNN", "modifiers0": [], "subject": ["Campus"], "modifiers1": [], "relation": ["is spread over"], "object": ["25 acres"], "modifiers2": [{"m_rel": ["of"], "m_obj": ["lush green land"]}, {"m_rel": ["in"], "m_obj": ["South Delhi"]}, {"m_rel": ["in"], "m_obj": ["Okhla Phase III", "Nehru Place"]}]}], " Campus is divided into 3 zones - Academic and Students\u2019 Area and Faculty Residences": [{"sentence": "NVVANNNCNNCNN", "modifiers0": [], "subject": ["Campus"], "modifiers1": [], "relation": ["is divided into"], "object": ["3 zones Academic", "Students Area", "Faculty Residences"], "modifiers2": []}], "Construction of phase II of Campus is in full swing": [{"sentence": "NANNANVANN", "modifiers0": [], "subject": ["Construction"], "modifiers1": [{"m_rel": ["of"], "m_obj": ["phase II"]}, {"m_rel": ["of"], "m_obj": ["Campus"]}], "relation": ["is in"], "object": ["full swing"], "modifiers2": []}], "The entire waste water generated in Campus is recycled using 2 sewage treatment plants with capacity of 65 KL per day and and water so generated is used for horticulture and flushing and air-conditioning works": [{"sentence": "NNNNAANVVANNNNANANNAN", "modifiers0": [], "subject": ["The entire waste water"], "modifiers1": [{"m_rel": ["generated in"], "m_obj": ["Campus"]}], "relation": ["is recycled using"], "object": ["2 sewage treatment plants"], "modifiers2": [{"m_rel": ["with"], "m_obj": ["capacity"]}, {"m_rel": ["of"], "m_obj": ["65 KL"]}, {"m_rel": ["per"], "m_obj": ["day"]}]}, {"sentence": "NVVVVANCNCNNN", "modifiers0": [], "subject": ["water"], "modifiers1": [], "relation": ["so generated is used for"], "object": ["horticulture", "flushing", "air conditioning works"], "modifiers2": []}], " A garbage segregation scheme for productive and safe disposal of solid waste has been worked out with local NGO.": [{"sentence": "NNNNANCNNANNVVVAANN", "modifiers0": [], "subject": ["A garbage segregation scheme"], "modifiers1": [{"m_rel": ["for"], "m_obj": ["productive", "safe disposal"]}, {"m_rel": ["of"], "m_obj": ["solid waste"]}], "relation": ["has been worked out with"], "object": ["local NGO"], "modifiers2": []}], "Eighty per cent of campus grounds are soft landscape (including some parking and circulation area)": [{"sentence": "NANANNVNNANNCNN", "modifiers0": [], "subject": ["Eighty"], "modifiers1": [{"m_rel": ["per"], "m_obj": ["cent"]}, {"m_rel": ["of"], "m_obj": ["campus grounds"]}], "relation": ["are"], "object": ["soft landscape"], "modifiers2": [{"m_rel": ["including"], "m_obj": ["some parking", "circulation area"]}]}], " Many of vehicular areas allow percolation": [{"sentence": "NANNVN", "modifiers0": [], "subject": ["Many"], "modifiers1": [{"m_rel": ["of"], "m_obj": ["vehicular areas"]}], "relation": ["allow"], "object": ["percolation"], "modifiers2": []}], " Rainwater harvesting pits and collection tanks have also been provided": [{"sentence": "NNNCNNVVVV", "modifiers0": [], "subject": ["Rainwater harvesting pits", "collection tanks"], "modifiers1": [], "relation": ["have also been provided"], "object": [], "modifiers2": []}], " All blocks are connected through layer 2 & 3 switches to provide 1 Gbit or s connectivity at user end": [{"sentence": "NNVVANN", "modifiers0": [], "subject": ["All blocks"], "modifiers1": [], "relation": ["are connected through"], "object": ["layer 2"], "modifiers2": []}, {"sentence": "NNNVNNCNNANN", "modifiers0": [], "subject": ["3 switches to"], "modifiers1": [], "relation": ["provide"], "object": ["1 Gbit", "s connectivity"], "modifiers2": [{"m_rel": ["at"], "m_obj": ["user end"]}]}], " Wireless network with 129 access points is also enabled in faculty block and library and classrooms and hostel blocks": [{"sentence": "NNANNNVVAANNCNCNCNN", "modifiers0": [], "subject": ["Wireless network"], "modifiers1": [{"m_rel": ["with"], "m_obj": ["129 access points"]}], "relation": ["is also enabled in"], "object": ["faculty block", "library", "classrooms", "hostel blocks"], "modifiers2": []}], "The Library and Information Center of Institute is housed in separate building": [{"sentence": "NNCNNANVVANN", "modifiers0": [], "subject": ["The Library", "Information Center"], "modifiers1": [{"m_rel": ["of"], "m_obj": ["Institute"]}], "relation": ["is housed in"], "object": ["separate building"], "modifiers2": []}], " The Library and Information is fully automated using RFID Technology with EM Security System": [{"sentence": "NNCNVVVANNANNN", "modifiers0": [], "subject": ["The Library", "Information"], "modifiers1": [], "relation": ["is fully automated using"], "object": ["RFID Technology"], "modifiers2": [{"m_rel": ["with"], "m_obj": ["EM Security System"]}]}], " The Library and Information has vast collection of print and electronic resources in area of interest.": [{"sentence": "NNCNVNNANCNNANAN", "modifiers0": [], "subject": ["The Library", "Information"], "modifiers1": [], "relation": ["has"], "object": ["vast collection"], "modifiers2": [{"m_rel": ["of"], "m_obj": ["print", "electronic resources"]}, {"m_rel": ["in"], "m_obj": ["area"]}, {"m_rel": ["of"], "m_obj": ["interest"]}]}], " Nehru Place and GK I or II and departmental store like Savemax at Kalkaji metro station provide for daily needs and clothing at competitive price": [{"sentence": "NNCNNCNCNNCNANNNVANNCNANN", "modifiers0": [], "subject": ["Nehru Place", "GK I", "II", "departmental store", "Savemax"], "modifiers1": [{"m_rel": ["at"], "m_obj": ["Kalkaji metro station"]}], "relation": ["provide for"], "object": ["daily needs", "clothing"], "modifiers2": [{"m_rel": ["at"], "m_obj": ["competitive price"]}]}], " Students take part in number of social and cultural activities": [{"sentence": "NVNANANCNN", "modifiers0": [], "subject": ["Students"], "modifiers1": [], "relation": ["take"], "object": ["part"], "modifiers2": [{"m_rel": ["in"], "m_obj": ["number"]}, {"m_rel": ["of"], "m_obj": ["social", "cultural activities"]}]}], " The clubs at IIIT- Delhi (IIIT Delhi) are based on adventure and music and software development and community work and dramatics and entrepreneurship and electronics and programming and game development and dance and painting and design and photography and chess and quizzing and sightseeing and public speaking and eco-development and more": [{"sentence": "NNANNNNVVANCNCNNCNNCNCNCNCNCNNCNCNCNCNCNCNCNCNNCNNCN", "modifiers0": [], "subject": ["The clubs"], "modifiers1": [{"m_rel": ["at"], "m_obj": ["IIIT- Delhi IIIT Delhi"]}], "relation": ["are based on"], "object": ["adventure", "music", "software development", "community work", "dramatics", "entrepreneurship", "electronics", "programming", "game development", "dance", "painting", "design", "photography", "chess", "quizzing", "sightseeing", "public speaking", "eco development", "more"], "modifiers2": []}], "Institute is equipped with number of indoor and outdoor sports facilities": [{"sentence": "NVVANANCNNN", "modifiers0": [], "subject": ["Institute"], "modifiers1": [], "relation": ["is equipped with"], "object": ["number"], "modifiers2": [{"m_rel": ["of"], "m_obj": ["indoor", "outdoor sports facilities"]}]}], " The top floor of Dining Block houses gymnasium and table tennis tables and and pool tables and while chess boards and carom boards are available in hostel common rooms": [{"sentence": "NNNANNNNCNNNCNNCNNCNNVNANNN", "modifiers0": [], "subject": ["The top floor"], "modifiers1": [{"m_rel": ["of"], "m_obj": ["Dining Block houses gymnasium", "table tennis tables", "pool tables", "chess boards", "carom boards"]}], "relation": ["are"], "object": ["available"], "modifiers2": [{"m_rel": ["in"], "m_obj": ["hostel common rooms"]}]}], " Institute currently has two tennis courts and basketball court and volleyball field and two badminton courts": [{"sentence": "NVVNNNCNNCNNCNNN", "modifiers0": [], "subject": ["Institute"], "modifiers1": [], "relation": ["currently has"], "object": ["two tennis courts", "basketball court", "volleyball field", "two badminton courts"], "modifiers2": []}], " The new sports block will be ready by end of 2017": [{"sentence": "NNNNVVNANAN", "modifiers0": [], "subject": ["The new sports block"], "modifiers1": [], "relation": ["will be"], "object": ["ready"], "modifiers2": [{"m_rel": ["by"], "m_obj": ["end"]}, {"m_rel": ["of"], "m_obj": ["2017"]}]}], " The new sports block will house indoor swimming pool and indoor badminton court and two squash courts.": [{"sentence": "NNNNVVNNNCNNNCNNN", "modifiers0": [], "subject": ["The new sports block"], "modifiers1": [], "relation": ["will house"], "object": ["indoor swimming pool", "indoor badminton court", "two squash courts"], "modifiers2": []}], " We also organize summer camps for various sports activities at IIIT Delhi campus": [{"sentence": "NVVNNANNNANNN", "modifiers0": [], "subject": ["We"], "modifiers1": [], "relation": ["also organize"], "object": ["summer camps"], "modifiers2": [{"m_rel": ["for"], "m_obj": ["various sports activities"]}, {"m_rel": ["at"], "m_obj": ["IIIT Delhi campus"]}]}], " A mega sport event and Triquetra and event jointly held by IIITD and NSIT and DTU every year.": [{"sentence": "NNNNCNCNVVANCNCNNN", "modifiers0": [], "subject": ["A mega sport event", "Triquetra", "event"], "modifiers1": [], "relation": ["jointly held by"], "object": ["IIITD", "NSIT", "DTU every year"], "modifiers2": []}], "The institute\u2019s gym is equipped with facilities like treadmills and cross-trainer and recumbent bike and abdominal machine and dumbbells and gravity expension.": [{"sentence": "NNNNVVANCNCNNNCNNCNNCNCNN", "modifiers0": [], "subject": ["The institute \u2019s gym"], "modifiers1": [], "relation": ["is equipped with"], "object": ["facilities", "treadmills", "cross - trainer", "recumbent bike", "abdominal machine", "dumbbells", "gravity expension"], "modifiers2": []}], " Students are organizing TEDxIIITD event since last three years and which was hugely successful with excellent young inspirational speakers.": [{"sentence": "NVVNNCNNN", "modifiers0": [], "subject": ["Students"], "modifiers1": [], "relation": ["are organizing"], "object": ["TEDxIIITD event", "last three years"], "modifiers2": []}, {"sentence": "NVVNANNNN", "modifiers0": [], "subject": ["which"], "modifiers1": [], "relation": ["was hugely"], "object": ["successful"], "modifiers2": [{"m_rel": ["with"], "m_obj": ["excellent young inspirational speakers"]}]}], " The cultural activities (arts and literary) for year are planned together by Student Council and Cultural Secretary": [{"sentence": "NNNNCNANVVVANNCNN", "modifiers0": [], "subject": ["The cultural activities arts", "literary"], "modifiers1": [{"m_rel": ["for"], "m_obj": ["year"]}], "relation": ["are planned together by"], "object": ["Student Council", "Cultural Secretary"], "modifiers2": []}], " Sharma are available at institute for sessions and meetings with students": [{"sentence": "NVNANANCNAN", "modifiers0": [], "subject": ["Sharma"], "modifiers1": [], "relation": ["are"], "object": ["available"], "modifiers2": [{"m_rel": ["at"], "m_obj": ["institute"]}, {"m_rel": ["for"], "m_obj": ["sessions", "meetings"]}, {"m_rel": ["with"], "m_obj": ["students"]}]}], " Such sessions and meetings are strictly private and confidential.": [{"sentence": "NNCNVVNCN", "modifiers0": [], "subject": ["Such sessions", "meetings"], "modifiers1": [], "relation": ["are strictly"], "object": ["private", "confidential"], "modifiers2": []}], " The campus counselors are there for your support and welfare": [{"sentence": "NNNVVANNCN", "modifiers0": [], "subject": ["The campus counselors"], "modifiers1": [], "relation": ["are there for"], "object": ["your support", "welfare"], "modifiers2": []}], " Some things and events may feel too much and you might feel overwhelmed": [{"sentence": "NNCNVVVN", "modifiers0": [], "subject": ["Some things", "events"], "modifiers1": [], "relation": ["may feel too"], "object": ["much"], "modifiers2": []}, {"sentence": "NVVN", "modifiers0": [], "subject": ["you"], "modifiers1": [], "relation": ["might feel"], "object": ["overwhelmed"], "modifiers2": []}], "Its important to avoid distractions": [{"sentence": "NNNVN", "modifiers0": [], "subject": ["Its important to"], "modifiers1": [], "relation": ["avoid"], "object": ["distractions"], "modifiers2": []}], " Sleep cycle also suffers leading to lot of unnecessary health issues": [{"sentence": "NNVVAANANNN", "modifiers0": [], "subject": ["Sleep cycle"], "modifiers1": [], "relation": ["also suffers leading to"], "object": ["lot"], "modifiers2": [{"m_rel": ["of"], "m_obj": ["unnecessary health issues"]}]}], " Each room is provided with furniture needed by student - bed and table and chair and bookshelf and cupboard and etc. The rooms are provided night time air conditioning in peak summers and and heating in peak winters": [{"sentence": "NNVVANAANNCNCNCNCN", "modifiers0": [], "subject": ["Each room"], "modifiers1": [], "relation": ["is provided with"], "object": ["furniture"], "modifiers2": [{"m_rel": ["needed by"], "m_obj": ["student bed", "table", "chair", "bookshelf", "cupboard"]}]}, {"sentence": "NNVVNNNNANNCNANN", "modifiers0": [], "subject": ["The rooms"], "modifiers1": [], "relation": ["are provided"], "object": ["night time air conditioning"], "modifiers2": [{"m_rel": ["in"], "m_obj": ["peak summers", "heating"]}, {"m_rel": ["in"], "m_obj": ["peak winters"]}]}], "There is common mess for boys and girls which functions during working semester": [{"sentence": "NVNNAN", "modifiers0": [], "subject": ["There"], "modifiers1": [], "relation": ["is"], "object": ["common mess"], "modifiers2": [{"m_rel": ["for"], "m_obj": ["boys"]}]}, {"sentence": "NNVANN", "modifiers0": [], "subject": ["girls which"], "modifiers1": [], "relation": ["functions during"], "object": ["working semester"], "modifiers2": []}], " Air conditioning is provided in common mess for boys and girls which functions during working semester during lunch time": [{"sentence": "NNVVANNAN", "modifiers0": [], "subject": ["Air conditioning"], "modifiers1": [], "relation": ["is provided in"], "object": ["common mess"], "modifiers2": [{"m_rel": ["for"], "m_obj": ["boys"]}]}, {"sentence": "NNVAANANN", "modifiers0": [], "subject": ["girls which"], "modifiers1": [], "relation": ["functions during working"], "object": ["semester"], "modifiers2": [{"m_rel": ["during"], "m_obj": ["lunch time"]}]}], " Common Room is equipped with TV and newspapers and magazines and many other facilities.": [{"sentence": "NNVVANCNCNCNNN", "modifiers0": [], "subject": ["Common Room"], "modifiers1": [], "relation": ["is equipped with"], "object": ["TV", "newspapers", "magazines", "many other facilities"], "modifiers2": []}], "An external security agency has been contracted for providing security at hostels": [{"sentence": "NNNNVVVAANAN", "modifiers0": [], "subject": ["An external security agency"], "modifiers1": [], "relation": ["has been contracted for providing"], "object": ["security"], "modifiers2": [{"m_rel": ["at"], "m_obj": ["hostels"]}]}], " The services of security personnel are monitored by GM-Facility Management Services (FMS)": [{"sentence": "NNANNVVANNNNN", "modifiers0": [], "subject": ["The services"], "modifiers1": [{"m_rel": ["of"], "m_obj": ["security personnel"]}], "relation": ["are monitored by"], "object": ["GM Facility Management Services FMS"], "modifiers2": []}], " Mess Committee Mess Committee monitors quality and taste and hygiene of food served in mess": [{"sentence": "NNNNVNCNCNANAAN", "modifiers0": [], "subject": ["Mess Committee Mess Committee"], "modifiers1": [], "relation": ["monitors"], "object": ["quality", "taste", "hygiene"], "modifiers2": [{"m_rel": ["of"], "m_obj": ["food"]}, {"m_rel": ["served in"], "m_obj": ["mess"]}]}], " Periodical review and inspection of quality of food items also form part of food items duties.": [{"sentence": "NNCNANANNVVNANNN", "modifiers0": [], "subject": ["Periodical review", "inspection"], "modifiers1": [{"m_rel": ["of"], "m_obj": ["quality"]}, {"m_rel": ["of"], "m_obj": ["food items"]}], "relation": ["also form"], "object": ["part"], "modifiers2": [{"m_rel": ["of"], "m_obj": ["food items duties"]}]}], " The points related to allotment are:": [{"sentence": "NNAANV", "modifiers0": [], "subject": ["The points"], "modifiers1": [{"m_rel": ["related to"], "m_obj": ["allotment"]}], "relation": ["are"], "object": [], "modifiers2": []}], "Rest will be allotted according to distance criteria from institute.": [{"sentence": "NVVVAANNAN", "modifiers0": [], "subject": ["Rest"], "modifiers1": [], "relation": ["will be allotted according to"], "object": ["distance criteria"], "modifiers2": [{"m_rel": ["from"], "m_obj": ["institute"]}]}], "Online applications are invited during vacations for existing students": [{"sentence": "NNVVANAAN", "modifiers0": [], "subject": ["Online applications"], "modifiers1": [], "relation": ["are invited during"], "object": ["vacations"], "modifiers2": [{"m_rel": ["for existing"], "m_obj": ["students"]}]}], " Hostel fees are revised annually.": [{"sentence": "NNVVV", "modifiers0": [], "subject": ["Hostel fees"], "modifiers1": [], "relation": ["are revised annually"], "object": [], "modifiers2": []}], "Mess charges may be between Rs 9 and 000 - Rs 11 and 500 for four months": [{"sentence": "NNVVANNCNNNCNANN", "modifiers0": [], "subject": ["Mess charges"], "modifiers1": [], "relation": ["may be between"], "object": ["Rs 9", "000 Rs 11", "500"], "modifiers2": [{"m_rel": ["for"], "m_obj": ["four months"]}]}], "Any act of intimidation or violence and willful damage to property and drunken riotous behavior constitute offence.": [{"sentence": "NNANCNCNNANCNNNVN", "modifiers0": [], "subject": ["Any act"], "modifiers1": [{"m_rel": ["of"], "m_obj": ["intimidation", "violence", "willful damage"]}, {"m_rel": ["to"], "m_obj": ["property", "drunken riotous behavior"]}], "relation": ["constitute"], "object": ["offence"], "modifiers2": []}], "Smoking and use of narcotics and consumption of alcoholic beverages and gambling are strictly prohibited.": [{"sentence": "NCNANCNANNCNVVV", "modifiers0": [], "subject": ["Smoking", "use"], "modifiers1": [{"m_rel": ["of"], "m_obj": ["narcotics", "consumption"]}, {"m_rel": ["of"], "m_obj": ["alcoholic beverages", "gambling"]}], "relation": ["are strictly prohibited"], "object": [], "modifiers2": []}], "A student\u2019s parents and other same-gender guests may visit student in his or her room from 8 am 8 pm": [{"sentence": "NNNNCNNNNVVNAN", "modifiers0": [], "subject": ["A student \u2019s parents", "other same gender guests"], "modifiers1": [], "relation": ["may visit"], "object": ["student"], "modifiers2": [{"m_rel": ["in"], "m_obj": ["his"]}]}, {"sentence": "NNANVNN", "modifiers0": [], "subject": ["her room"], "modifiers1": [{"m_rel": ["from"], "m_obj": ["8"]}], "relation": ["am"], "object": ["8 pm"], "modifiers2": []}], " Any other visitor can only be met in common room of hostel": [{"sentence": "NNNVVVVANNAN", "modifiers0": [], "subject": ["Any other visitor"], "modifiers1": [], "relation": ["can only be met in"], "object": ["common room"], "modifiers2": [{"m_rel": ["of"], "m_obj": ["hostel"]}]}], " Hostel related communications shall be done via admin-hostel@ iiwitd.ac.in": [{"sentence": "NNNVVVANN", "modifiers0": [], "subject": ["Hostel related communications"], "modifiers1": [], "relation": ["shall be done via"], "object": ["admin iiwitd.ac.in"], "modifiers2": []}], " Qualified Medical Practitioner (B.Sc and MBBS and FCPG) is be available in our premises six days week from Monday to Saturday between 15:00-16:00 Hrs": [{"sentence": "NNNNCNCNVVNANNNNNANANANNN", "modifiers0": [], "subject": ["Qualified Medical Practitioner B.Sc", "MBBS", "FCPG"], "modifiers1": [], "relation": ["is be"], "object": ["available"], "modifiers2": [{"m_rel": ["in"], "m_obj": ["our premises six days week"]}, {"m_rel": ["from"], "m_obj": ["Monday"]}, {"m_rel": ["to"], "m_obj": ["Saturday"]}, {"m_rel": ["between"], "m_obj": ["15:00 16:00 Hrs"]}]}], " First Aid kits are available with guards posted in Academic and hostel blocks by dialling security\u2019s extension number 592": [{"sentence": "NNNVNANAANCNNAANNNNN", "modifiers0": [], "subject": ["First Aid kits"], "modifiers1": [], "relation": ["are"], "object": ["available"], "modifiers2": [{"m_rel": ["with"], "m_obj": ["guards"]}, {"m_rel": ["posted in"], "m_obj": ["Academic", "hostel blocks"]}, {"m_rel": ["by dialling"], "m_obj": ["security \u2019s extension number 592"]}]}], " The hospital offers treatment in areas of healthcare except those needing Intensive Care facilities": [{"sentence": "NNVNANANCNANNN", "modifiers0": [], "subject": ["The hospital"], "modifiers1": [], "relation": ["offers"], "object": ["treatment"], "modifiers2": [{"m_rel": ["in"], "m_obj": ["areas"]}, {"m_rel": ["of"], "m_obj": ["healthcare", "those"]}, {"m_rel": ["needing"], "m_obj": ["Intensive Care facilities"]}]}], " Any student requiring Intensive care can be transferred to The hospital by Hospital Ambulance": [{"sentence": "NNANNVVVANNANN", "modifiers0": [], "subject": ["Any student"], "modifiers1": [{"m_rel": ["requiring"], "m_obj": ["Intensive care"]}], "relation": ["can be transferred to"], "object": ["The hospital"], "modifiers2": [{"m_rel": ["by"], "m_obj": ["Hospital Ambulance"]}]}], "It is 40-bed hospital with 24 hrs ICU and Emergency backup": [{"sentence": "NVNNANNNCNN", "modifiers0": [], "subject": ["It"], "modifiers1": [], "relation": ["is"], "object": ["40-bed hospital"], "modifiers2": [{"m_rel": ["with"], "m_obj": ["24 hrs ICU", "Emergency backup"]}]}], " It provides Free 24 hr Ambulance Services in case of emergency": [{"sentence": "NVNNNNNANAN", "modifiers0": [], "subject": ["It"], "modifiers1": [], "relation": ["provides"], "object": ["Free 24 hr Ambulance Services"], "modifiers2": [{"m_rel": ["in"], "m_obj": ["case"]}, {"m_rel": ["of"], "m_obj": ["emergency"]}]}], " The subsidized charges for IIIT-Delhi student in OPD are Rs 150 or -per consultation": [{"sentence": "NNNANNNANVNNCN", "modifiers0": [], "subject": ["The subsidized charges"], "modifiers1": [{"m_rel": ["for"], "m_obj": ["IIIT Delhi student"]}, {"m_rel": ["in"], "m_obj": ["OPD"]}], "relation": ["are"], "object": ["Rs 150", "consultation"], "modifiers2": []}], " The hospital phone number is 49922222.": [{"sentence": "NNNNVN", "modifiers0": [], "subject": ["The hospital phone number"], "modifiers1": [], "relation": ["is"], "object": ["49922222"], "modifiers2": []}], "It is at forefront of medical technology and expertise": [{"sentence": "NVANANNCN", "modifiers0": [], "subject": ["It"], "modifiers1": [], "relation": ["is at"], "object": ["forefront"], "modifiers2": [{"m_rel": ["of"], "m_obj": ["medical technology", "expertise"]}]}], " It provides complete range of latest diagnostic and medical and surgical facilities for care of It patients": [{"sentence": "NVNNANNCN", "modifiers0": [], "subject": ["It"], "modifiers1": [], "relation": ["provides"], "object": ["complete range"], "modifiers2": [{"m_rel": ["of"], "m_obj": ["latest diagnostic", "medical"]}]}, {"sentence": "NNANANV", "modifiers0": [], "subject": ["surgical facilities"], "modifiers1": [{"m_rel": ["for"], "m_obj": ["care"]}, {"m_rel": ["of"], "m_obj": ["It"]}], "relation": ["patients"], "object": [], "modifiers2": []}], " The hospital offers 10% Discount on Standard Apollo Health Check Packages for students and 5% discount on in-patient services on Room Rent & Investigations (Except Critical Care Beds)": [{"sentence": "NNVNNNANNNNNANCNNNAANNANNCNCNNN", "modifiers0": [], "subject": ["The hospital"], "modifiers1": [], "relation": ["offers"], "object": ["10 % Discount"], "modifiers2": [{"m_rel": ["on"], "m_obj": ["Standard Apollo Health Check Packages"]}, {"m_rel": ["for"], "m_obj": ["students", "5 % discount"]}, {"m_rel": ["on in"], "m_obj": ["patient services"]}, {"m_rel": ["on"], "m_obj": ["Room Rent", "Investigations", "Critical Care Beds"]}]}], " The hospital extends personal assistance in admissions and treatment": [{"sentence": "NNVNNANCN", "modifiers0": [], "subject": ["The hospital"], "modifiers1": [], "relation": ["extends"], "object": ["personal assistance"], "modifiers2": [{"m_rel": ["in"], "m_obj": ["admissions", "treatment"]}]}], "A shop for basic supplies has been opened on ground floor of Dining block and which also offers photocopying or scanning facilities on payment basis": [{"sentence": "NNANNVVVANNANN", "modifiers0": [], "subject": ["A shop"], "modifiers1": [{"m_rel": ["for"], "m_obj": ["basic supplies"]}], "relation": ["has been opened on"], "object": ["ground floor"], "modifiers2": [{"m_rel": ["of"], "m_obj": ["Dining block"]}]}, {"sentence": "NVVACANANN", "modifiers0": [], "subject": ["which"], "modifiers1": [], "relation": ["also offers"], "object": [], "modifiers2": [{"m_rel": ["photocopying", "scanning"], "m_obj": ["facilities"]}, {"m_rel": ["on"], "m_obj": ["payment basis"]}]}], " The students may also visit nearby markets in Govindpuri and Kalkaji and Nehru Place for purchasing consumer goods and other necessities": [{"sentence": "NNVVVNNANCNCNNAANNCNN", "modifiers0": [], "subject": ["The students"], "modifiers1": [], "relation": ["may also visit"], "object": ["nearby markets"], "modifiers2": [{"m_rel": ["in"], "m_obj": ["Govindpuri", "Kalkaji", "Nehru Place"]}, {"m_rel": ["for purchasing"], "m_obj": ["consumer goods", "other necessities"]}]}], "HDFC ATM is located on ground floor of dining block and Andhra Bank ATM in Ground Floor of Academic Building": [{"sentence": "NNVVANNANNCNNNANNANN", "modifiers0": [], "subject": ["HDFC ATM"], "modifiers1": [], "relation": ["is located on"], "object": ["ground floor"], "modifiers2": [{"m_rel": ["of"], "m_obj": ["dining block", "Andhra Bank ATM"]}, {"m_rel": ["in"], "m_obj": ["Ground Floor"]}, {"m_rel": ["of"], "m_obj": ["Academic Building"]}]}], " Some classes can also be arranged on Saturdays": [{"sentence": "NNVVVVAN", "modifiers0": [], "subject": ["Some classes"], "modifiers1": [], "relation": ["can also be arranged on"], "object": ["Saturdays"], "modifiers2": []}], " B.Tech labs on second floor of library building are accessible to under- graduate students and who may also get access for M.Tech labs at discretion of faculty": [{"sentence": "NNANNANNVNANNN", "modifiers0": [], "subject": ["B.Tech labs"], "modifiers1": [{"m_rel": ["on"], "m_obj": ["second floor"]}, {"m_rel": ["of"], "m_obj": ["library building"]}], "relation": ["are"], "object": ["accessible"], "modifiers2": [{"m_rel": ["to"], "m_obj": ["under- graduate students"]}]}, {"sentence": "NVVVNANNANAN", "modifiers0": [], "subject": ["who"], "modifiers1": [], "relation": ["may also get"], "object": ["access"], "modifiers2": [{"m_rel": ["for"], "m_obj": ["M.Tech labs"]}, {"m_rel": ["at"], "m_obj": ["discretion"]}, {"m_rel": ["of"], "m_obj": ["faculty"]}]}], " E-mail Ids within institute\u2019s domain are created for new students by IT department": [{"sentence": "NNNNANNNVVANNANN", "modifiers0": [], "subject": ["E - mail Ids"], "modifiers1": [{"m_rel": ["within"], "m_obj": ["institute \u2019s domain"]}], "relation": ["are created for"], "object": ["new students"], "modifiers2": [{"m_rel": ["by"], "m_obj": ["IT department"]}]}], "Attendance is taken in core courses": [{"sentence": "NVVANN", "modifiers0": [], "subject": ["Attendance"], "modifiers1": [], "relation": ["is taken in"], "object": ["core courses"], "modifiers2": []}], "All above documents are available at http://www.iiitd.ac.in/education/ resources": [{"sentence": "NANVNANN", "modifiers0": [], "subject": ["All"], "modifiers1": [{"m_rel": ["above"], "m_obj": ["documents"]}], "relation": ["are"], "object": ["available"], "modifiers2": [{"m_rel": ["at"], "m_obj": ["http://www.iiitd.ac.in/education/ resources"]}]}], " All evaluations are responsibility of assigned Instructor": [{"sentence": "NNVNANN", "modifiers0": [], "subject": ["All evaluations"], "modifiers1": [], "relation": ["are"], "object": ["responsibility"], "modifiers2": [{"m_rel": ["of"], "m_obj": ["assigned Instructor"]}]}], " All leave is approved by DOAA": [{"sentence": "NNVVAN", "modifiers0": [], "subject": ["All leave"], "modifiers1": [], "relation": ["is approved by"], "object": ["DOAA"], "modifiers2": []}], " Maximum duration of leave is defined in UG or PG regulations.": [{"sentence": "NNANVVANCNN", "modifiers0": [], "subject": ["Maximum duration"], "modifiers1": [{"m_rel": ["of"], "m_obj": ["leave"]}], "relation": ["is defined in"], "object": ["UG", "PG regulations"], "modifiers2": []}], " No late information will be considered.": [{"sentence": "NNNVVV", "modifiers0": [], "subject": ["No late information"], "modifiers1": [], "relation": ["will be considered"], "object": [], "modifiers2": []}], " Medical certificate may be verified from concerned Doctor.": [{"sentence": "NNVVVANN", "modifiers0": [], "subject": ["Medical certificate"], "modifiers1": [], "relation": ["may be verified from"], "object": ["concerned Doctor"], "modifiers2": []}], " Medical certificate will be sent to DOAA for approval.": [{"sentence": "NNVVVANAN", "modifiers0": [], "subject": ["Medical certificate"], "modifiers1": [], "relation": ["will be sent to"], "object": ["DOAA"], "modifiers2": [{"m_rel": ["for"], "m_obj": ["approval"]}]}], " Details are available on https://www. iiitd.ac.in or admission or btech-scholarship": [{"sentence": "NVNANNCNCNN", "modifiers0": [], "subject": ["Details"], "modifiers1": [], "relation": ["are"], "object": ["available"], "modifiers2": [{"m_rel": ["on"], "m_obj": ["https://www iiitd.ac.in", "admission", "btech scholarship"]}]}], " Delhi students whose JEE rank is less than 2000 will get Chairman\u2019s Scholarship for first year": [{"sentence": "NNNNNVN", "modifiers0": [], "subject": ["Delhi students whose JEE rank"], "modifiers1": [], "relation": ["is"], "object": ["less"], "modifiers2": []}, {"sentence": "NVVNNNANN", "modifiers0": [], "subject": ["2000"], "modifiers1": [], "relation": ["will get"], "object": ["Chairman \u2019s Scholarship"], "modifiers2": [{"m_rel": ["for"], "m_obj": ["first year"]}]}], "Caution Fees: Rs. 10 and 000 or - (one-time payment which is refundable) Hostel Fees: Rs. 64 and 000 or - per annum for single occupancy": [{"sentence": "NNNNNCNCNNNNVNNNNNCNCNNANN", "modifiers0": [], "subject": ["Caution Fees Rs . 10", "000", "one time payment which"], "modifiers1": [], "relation": ["is"], "object": ["refundable Hostel Fees Rs 64", "000", "per annum"], "modifiers2": [{"m_rel": ["for"], "m_obj": ["single occupancy"]}]}], " Students should follow policies formulated by institute from time to time for mutual benefit of two sides": [{"sentence": "NVVNAANANANANNANN", "modifiers0": [], "subject": ["Students"], "modifiers1": [], "relation": ["should follow"], "object": ["policies"], "modifiers2": [{"m_rel": ["formulated by"], "m_obj": ["institute"]}, {"m_rel": ["from"], "m_obj": ["time"]}, {"m_rel": ["to"], "m_obj": ["time"]}, {"m_rel": ["for"], "m_obj": ["mutual benefit"]}, {"m_rel": ["of"], "m_obj": ["two sides"]}]}], " Most of policies are given in this section.": [{"sentence": "NANVVANN", "modifiers0": [], "subject": ["Most"], "modifiers1": [{"m_rel": ["of"], "m_obj": ["policies"]}], "relation": ["are given in"], "object": ["this section"], "modifiers2": []}], "All vehicles entering Campus shall do so from Gate No 1": [{"sentence": "NNANVVVANNN", "modifiers0": [], "subject": ["All vehicles"], "modifiers1": [{"m_rel": ["entering"], "m_obj": ["Campus"]}], "relation": ["shall do so from"], "object": ["Gate No 1"], "modifiers2": []}], " The vehicles entering Campus shall keep The vehicles entering campus to left of road": [{"sentence": "NNANVVNNANANAN", "modifiers0": [], "subject": ["The vehicles"], "modifiers1": [{"m_rel": ["entering"], "m_obj": ["Campus"]}], "relation": ["shall keep"], "object": ["The vehicles"], "modifiers2": [{"m_rel": ["entering"], "m_obj": ["campus"]}, {"m_rel": ["to"], "m_obj": ["left"]}, {"m_rel": ["of"], "m_obj": ["road"]}]}], " Campus is No Horn Zone and maximum speed of 20 km or hr is permissible": [{"sentence": "NVNNNCNNANN", "modifiers0": [], "subject": ["Campus"], "modifiers1": [], "relation": ["is"], "object": ["No Horn Zone", "maximum speed"], "modifiers2": [{"m_rel": ["of"], "m_obj": ["20 km"]}]}, {"sentence": "NVN", "modifiers0": [], "subject": ["hr"], "modifiers1": [], "relation": ["is"], "object": ["permissible"], "modifiers2": []}], " The complete vehicle and parking policy is appended to end of this document (Appendix-I)": [{"sentence": "NNNCNNVVNNANNNN", "modifiers0": [], "subject": ["The complete vehicle", "parking policy"], "modifiers1": [], "relation": ["is appended"], "object": ["to end"], "modifiers2": [{"m_rel": ["of"], "m_obj": ["this document Appendix I"]}]}], " IT Policy is appended to end of this handbook (Appendix-III)": [{"sentence": "NNVVNNANNNN", "modifiers0": [], "subject": ["IT Policy"], "modifiers1": [], "relation": ["is appended"], "object": ["to end"], "modifiers2": [{"m_rel": ["of"], "m_obj": ["this handbook Appendix III"]}]}], " The student charter containing model code of conduct is appended to end of this document (Appendix-V).": [{"sentence": "NNNANNANVVNNANNNN", "modifiers0": [], "subject": ["The student charter"], "modifiers1": [{"m_rel": ["containing"], "m_obj": ["model code"]}, {"m_rel": ["of"], "m_obj": ["conduct"]}], "relation": ["is appended"], "object": ["to end"], "modifiers2": [{"m_rel": ["of"], "m_obj": ["this document Appendix V"]}]}], "Student Council has two (or three) representatives from each branch for every UG and PG batch who are elected every year": [{"sentence": "NNVNCNNANNANN", "modifiers0": [], "subject": ["Student Council"], "modifiers1": [], "relation": ["has"], "object": ["two", "three representatives"], "modifiers2": [{"m_rel": ["from"], "m_obj": ["each branch"]}, {"m_rel": ["for"], "m_obj": ["every UG"]}]}, {"sentence": "NNNVVNN", "modifiers0": [], "subject": ["PG batch who"], "modifiers1": [], "relation": ["are elected"], "object": ["every year"], "modifiers2": []}], "to safeguard and promote academic interests of students": [{"sentence": "NVCVNNAN", "modifiers0": [], "subject": ["to"], "modifiers1": [], "relation": ["safeguard", "promote"], "object": ["academic interests"], "modifiers2": [{"m_rel": ["of"], "m_obj": ["students"]}]}], "to maintain and assist active engagement for students in academics": [{"sentence": "NVCVNNANAN", "modifiers0": [], "subject": ["to"], "modifiers1": [], "relation": ["maintain", "assist"], "object": ["active engagement"], "modifiers2": [{"m_rel": ["for"], "m_obj": ["students"]}, {"m_rel": ["in"], "m_obj": ["academics"]}]}], " The Student Senate coordinator is responsible for representation of Student Senate in Student Council and UGC and institute\u2019s Senate": [{"sentence": "NNNNVNANANNANNCNCNNN", "modifiers0": [], "subject": ["The Student Senate coordinator"], "modifiers1": [], "relation": ["is"], "object": ["responsible"], "modifiers2": [{"m_rel": ["for"], "m_obj": ["representation"]}, {"m_rel": ["of"], "m_obj": ["Student Senate"]}, {"m_rel": ["in"], "m_obj": ["Student Council", "UGC", "institute \u2019s Senate"]}]}], " The Secretary is responsible for internal coordination within Student Senate": [{"sentence": "NNVNANNANN", "modifiers0": [], "subject": ["The Secretary"], "modifiers1": [], "relation": ["is"], "object": ["responsible"], "modifiers2": [{"m_rel": ["for"], "m_obj": ["internal coordination"]}, {"m_rel": ["within"], "m_obj": ["Student Senate"]}]}], "To facilitate communication between students and faculty and and administration of institute.": [{"sentence": "NVNANCNCNAN", "modifiers0": [], "subject": ["To"], "modifiers1": [], "relation": ["facilitate"], "object": ["communication"], "modifiers2": [{"m_rel": ["between"], "m_obj": ["students", "faculty", "administration"]}, {"m_rel": ["of"], "m_obj": ["institute"]}]}], "To represent interests and concerns of students to institute.": [{"sentence": "NVNCNANAN", "modifiers0": [], "subject": ["To"], "modifiers1": [], "relation": ["represent"], "object": ["interests", "concerns"], "modifiers2": [{"m_rel": ["of"], "m_obj": ["students"]}, {"m_rel": ["to"], "m_obj": ["institute"]}]}], "To improve quality of student life at institute.": [{"sentence": "NVNANNAN", "modifiers0": [], "subject": ["To"], "modifiers1": [], "relation": ["improve"], "object": ["quality"], "modifiers2": [{"m_rel": ["of"], "m_obj": ["student life"]}, {"m_rel": ["at"], "m_obj": ["institute"]}]}], "Students may approach different people for different types of grievances": [{"sentence": "NVVNNANNAN", "modifiers0": [], "subject": ["Students"], "modifiers1": [], "relation": ["may approach"], "object": ["different people"], "modifiers2": [{"m_rel": ["for"], "m_obj": ["different types"]}, {"m_rel": ["of"], "m_obj": ["grievances"]}]}], "Course Related Academics Related": [{"sentence": "NNNV", "modifiers0": [], "subject": ["Course Related Academics"], "modifiers1": [], "relation": ["Related"], "object": [], "modifiers2": []}], "Hostels or Facilities related": [{"sentence": "NCNV", "modifiers0": [], "subject": ["Hostels", "Facilities"], "modifiers1": [], "relation": ["related"], "object": [], "modifiers2": []}], "Campus life is about trying new things": [{"sentence": "NNVAANN", "modifiers0": [], "subject": ["Campus life"], "modifiers1": [], "relation": ["is about trying"], "object": ["new things"], "modifiers2": []}], "Attend classes regularly": [{"sentence": "NNV", "modifiers0": [], "subject": ["Attend classes"], "modifiers1": [], "relation": ["regularly"], "object": [], "modifiers2": []}], "The induction cum Orientation for new students is must-": [{"sentence": "NNNNANNVN", "modifiers0": [], "subject": ["The induction cum Orientation"], "modifiers1": [{"m_rel": ["for"], "m_obj": ["new students"]}], "relation": ["is"], "object": ["must-"], "modifiers2": []}], "work done": [{"sentence": "NV", "modifiers0": [], "subject": ["work"], "modifiers1": [], "relation": ["done"], "object": [], "modifiers2": []}], " Partying in moderation is okay.": [{"sentence": "NANVN", "modifiers0": [], "subject": ["Partying"], "modifiers1": [{"m_rel": ["in"], "m_obj": ["moderation"]}], "relation": ["is"], "object": ["okay"], "modifiers2": []}], "Smoking and consumption of alcohol is strictly prohibited on campus.": [{"sentence": "NCNANVVAAN", "modifiers0": [], "subject": ["Smoking", "consumption"], "modifiers1": [{"m_rel": ["of"], "m_obj": ["alcohol"]}], "relation": ["is strictly prohibited on"], "object": ["campus"], "modifiers2": []}], "buildings are under CCTV surveillance and and damage caused to Damaging institute\u2019s property": [{"sentence": "NVANNCNAANNNN", "modifiers0": [], "subject": ["buildings"], "modifiers1": [], "relation": ["are under"], "object": ["CCTV surveillance", "damage"], "modifiers2": [{"m_rel": ["caused to"], "m_obj": ["Damaging institute \u2019s property"]}]}], "property will be charged from those responsible in addition to disciplinary actions.": [{"sentence": "NVVVANNANANN", "modifiers0": [], "subject": ["property"], "modifiers1": [], "relation": ["will be charged from"], "object": ["those responsible"], "modifiers2": [{"m_rel": ["in"], "m_obj": ["addition"]}, {"m_rel": ["to"], "m_obj": ["disciplinary actions"]}]}], "You may hire taxi from Airport": [{"sentence": "NVVNAN", "modifiers0": [], "subject": ["You"], "modifiers1": [], "relation": ["may hire"], "object": ["taxi"], "modifiers2": [{"m_rel": ["from"], "m_obj": ["Airport"]}]}], " There is pre-paid taxi counter inside Airport": [{"sentence": "NVNNNNNAN", "modifiers0": [], "subject": ["There"], "modifiers1": [], "relation": ["is"], "object": ["pre - paid taxi counter"], "modifiers2": [{"m_rel": ["inside"], "m_obj": ["Airport"]}]}], " The travel time from Airport is approximately 45-50 min.": [{"sentence": "NNNANVVNNN", "modifiers0": [], "subject": ["The travel time"], "modifiers1": [{"m_rel": ["from"], "m_obj": ["Airport"]}], "relation": ["is approximately"], "object": ["45 50 min"], "modifiers2": []}], "You may hire taxi from New Delhi Railway Station": [{"sentence": "NVVNANNNN", "modifiers0": [], "subject": ["You"], "modifiers1": [], "relation": ["may hire"], "object": ["taxi"], "modifiers2": [{"m_rel": ["from"], "m_obj": ["New Delhi Railway Station"]}]}], " The travel time from New Delhi Railway Station is approximately 40-45 min": [{"sentence": "NNNANNNNVVNNN", "modifiers0": [], "subject": ["The travel time"], "modifiers1": [{"m_rel": ["from"], "m_obj": ["New Delhi Railway Station"]}], "relation": ["is approximately"], "object": ["40 45 min"], "modifiers2": []}], " The Accounts Section will send email to fresh students and help in opening fresh students bank accounts": [{"sentence": "NNNVVNANNCNAANNNN", "modifiers0": [], "subject": ["The Accounts Section"], "modifiers1": [], "relation": ["will send"], "object": ["email"], "modifiers2": [{"m_rel": ["to"], "m_obj": ["fresh students", "help"]}, {"m_rel": ["in opening"], "m_obj": ["fresh students bank accounts"]}]}], " Bank Account is located in Okhla Industrial Area and Phase-3": [{"sentence": "NNVVANNNCN", "modifiers0": [], "subject": ["Bank Account"], "modifiers1": [], "relation": ["is located in"], "object": ["Okhla Industrial Area", "Phase-3"], "modifiers2": []}], "You can get basic information from https://iiitd.ac.in/academics/courses": [{"sentence": "NVVNNAN", "modifiers0": [], "subject": ["You"], "modifiers1": [], "relation": ["can get"], "object": ["basic information"], "modifiers2": [{"m_rel": ["from"], "m_obj": ["https://iiitd.ac.in/academics/courses"]}]}], "Whom to contact for NOC regarding internship?": [{"sentence": "NNVANAN", "modifiers0": [], "subject": ["Whom to"], "modifiers1": [], "relation": ["contact for"], "object": ["NOC"], "modifiers2": [{"m_rel": ["regarding"], "m_obj": ["internship"]}]}], "Whom to contact for E-mail and other IT-related services?": [{"sentence": "NNVANNN", "modifiers0": [], "subject": ["Whom to"], "modifiers1": [], "relation": ["contact for"], "object": ["E - mail"], "modifiers2": []}, {"sentence": "NNVN", "modifiers0": [], "subject": ["other IT"], "modifiers1": [], "relation": ["related"], "object": ["services"], "modifiers2": []}], "Whom to contact for lost or found property?": [{"sentence": "NNVAVCVN", "modifiers0": [], "subject": ["Whom to"], "modifiers1": [], "relation": ["contact for lost", "found"], "object": ["property"], "modifiers2": []}], "FMS division in Service block may be contacted in this connection.": [{"sentence": "NNANNVVVANN", "modifiers0": [], "subject": ["FMS division"], "modifiers1": [{"m_rel": ["in"], "m_obj": ["Service block"]}], "relation": ["may be contacted in"], "object": ["this connection"], "modifiers2": []}], "Any other query and not specified above?": [{"sentence": "NNNCNVV", "modifiers0": [], "subject": ["Any other query", "not"], "modifiers1": [], "relation": ["specified above"], "object": [], "modifiers2": []}], " The list of options offered is given below:": [{"sentence": "NNANVVVV", "modifiers0": [], "subject": ["The list"], "modifiers1": [{"m_rel": ["of"], "m_obj": ["options"]}], "relation": ["offered is given below"], "object": [], "modifiers2": []}], " An internship in start up can really be very helpful.": [{"sentence": "NNANAVVVVN", "modifiers0": [], "subject": ["An internship"], "modifiers1": [{"m_rel": ["in"], "m_obj": ["start"]}], "relation": ["up can really be very"], "object": ["helpful"], "modifiers2": []}], "A high CGPA is highly desirable.": [{"sentence": "NNNVVN", "modifiers0": [], "subject": ["A high CGPA"], "modifiers1": [], "relation": ["is highly"], "object": ["desirable"], "modifiers2": []}], "This is effectively same as engineering career route": [{"sentence": "NVVNCNNN", "modifiers0": [], "subject": ["This"], "modifiers1": [], "relation": ["is effectively"], "object": ["same", "engineering career route"], "modifiers2": []}], " Problem solving skills will still be highly valued": [{"sentence": "NANVVVVV", "modifiers0": [], "subject": ["Problem"], "modifiers1": [{"m_rel": ["solving"], "m_obj": ["skills"]}], "relation": ["will still be highly valued"], "object": [], "modifiers2": []}], "The three main effective study practices that emerged are:": [{"sentence": "NNNNNNNVV", "modifiers0": [], "subject": ["The three main effective study practices that"], "modifiers1": [], "relation": ["emerged are"], "object": [], "modifiers2": []}], "The two aspect of this practice are": [{"sentence": "NNNANNV", "modifiers0": [], "subject": ["The two aspect"], "modifiers1": [{"m_rel": ["of"], "m_obj": ["this practice"]}], "relation": ["are"], "object": [], "modifiers2": []}], "(i) attend lectures and": [{"sentence": "NVN", "modifiers0": [], "subject": ["i"], "modifiers1": [], "relation": ["attend"], "object": ["lectures"], "modifiers2": []}], "Many prefer individual study": [{"sentence": "NVNN", "modifiers0": [], "subject": ["Many"], "modifiers1": [], "relation": ["prefer"], "object": ["individual study"], "modifiers2": []}], "Explaintothemas explaining helps other students": [{"sentence": "NNVNN", "modifiers0": [], "subject": ["Explaintothemas explaining"], "modifiers1": [], "relation": ["helps"], "object": ["other students"], "modifiers2": []}], "Academics gets first priority": [{"sentence": "NVNN", "modifiers0": [], "subject": ["Academics"], "modifiers1": [], "relation": ["gets"], "object": ["first priority"], "modifiers2": []}], " Prioritizing is very important": [{"sentence": "NVVN", "modifiers0": [], "subject": ["Prioritizing"], "modifiers1": [], "relation": ["is very"], "object": ["important"], "modifiers2": []}], " It is as simple as that. we should make good use of time": [{"sentence": "NVVN", "modifiers0": [], "subject": ["It"], "modifiers1": [], "relation": ["is as"], "object": ["simple"], "modifiers2": []}, {"sentence": "NNVVNNAN", "modifiers0": [], "subject": ["that we"], "modifiers1": [], "relation": ["should make"], "object": ["good use"], "modifiers2": [{"m_rel": ["of"], "m_obj": ["time"]}]}], " We should consider We non academic interest as 6th course and schedule 6th course 10 hrs too": [{"sentence": "NVVNNNNCNN", "modifiers0": [], "subject": ["We"], "modifiers1": [], "relation": ["should consider"], "object": ["We non academic interest", "6th course"], "modifiers2": []}, {"sentence": "NNNNNV", "modifiers0": [], "subject": ["schedule 6th course 10 hrs"], "modifiers1": [], "relation": ["too"], "object": [], "modifiers2": []}], " No distractions at all": [{"sentence": "NNVV", "modifiers0": [], "subject": ["No distractions"], "modifiers1": [], "relation": ["at all"], "object": [], "modifiers2": []}], "B.Tech is not My Cup of Tea": [{"sentence": "NVNNNAN", "modifiers0": [], "subject": ["B.Tech"], "modifiers1": [], "relation": ["is"], "object": ["not My Cup"], "modifiers2": [{"m_rel": ["of"], "m_obj": ["Tea"]}]}], " There is always bigger picture": [{"sentence": "NVVNN", "modifiers0": [], "subject": ["There"], "modifiers1": [], "relation": ["is always"], "object": ["bigger picture"], "modifiers2": []}], " You may go little easy for while.": [{"sentence": "NVVNNAN", "modifiers0": [], "subject": ["You"], "modifiers1": [], "relation": ["may go"], "object": ["little easy"], "modifiers2": [{"m_rel": ["for"], "m_obj": ["while"]}]}], " Engineering can be applied in spheres of life": [{"sentence": "NVVVANAN", "modifiers0": [], "subject": ["Engineering"], "modifiers1": [], "relation": ["can be applied in"], "object": ["spheres"], "modifiers2": [{"m_rel": ["of"], "m_obj": ["life"]}]}], " It depends on you": [{"sentence": "NVAN", "modifiers0": [], "subject": ["It"], "modifiers1": [], "relation": ["depends on"], "object": ["you"], "modifiers2": []}], " Use office hours effectively and bug professors till time concept is clear to you.": [{"sentence": "NNNV", "modifiers0": [], "subject": ["Use office hours"], "modifiers1": [], "relation": ["effectively"], "object": [], "modifiers2": []}, {"sentence": "NNCNNVNAN", "modifiers0": [], "subject": ["bug professors", "time concept"], "modifiers1": [], "relation": ["is"], "object": ["clear"], "modifiers2": [{"m_rel": ["to"], "m_obj": ["you"]}]}], " A change can often trigger interest and understanding": [{"sentence": "NNVVVNCN", "modifiers0": [], "subject": ["A change"], "modifiers1": [], "relation": ["can often trigger"], "object": ["interest", "understanding"], "modifiers2": []}], " Self study is must": [{"sentence": "NNVV", "modifiers0": [], "subject": ["Self study"], "modifiers1": [], "relation": ["is must"], "object": [], "modifiers2": []}], " Courses like Introduction to Programming and DSA and Probability and and Algebra need better and fine understanding since other courses are based on other courses": [{"sentence": "NCNANCNCNCNVNCNN", "modifiers0": [], "subject": ["Courses", "Introduction"], "modifiers1": [{"m_rel": ["to"], "m_obj": ["Programming", "DSA", "Probability", "Algebra"]}], "relation": ["need"], "object": ["better", "fine understanding"], "modifiers2": []}, {"sentence": "NNVVANN", "modifiers0": [], "subject": ["other courses"], "modifiers1": [], "relation": ["are based on"], "object": ["other courses"], "modifiers2": []}], " Practice as much as you can": [{"sentence": "NVV", "modifiers0": [], "subject": ["Practice"], "modifiers1": [], "relation": ["as much"], "object": [], "modifiers2": []}, {"sentence": "NV", "modifiers0": [], "subject": ["you"], "modifiers1": [], "relation": ["can"], "object": [], "modifiers2": []}], "Target problems for which you know solution - sorting and searching and and traversals": [{"sentence": "NNANNVNNCNCN", "modifiers0": [], "subject": ["Target problems"], "modifiers1": [{"m_rel": ["for"], "m_obj": ["which you"]}], "relation": ["know"], "object": ["solution sorting", "searching", "traversals"], "modifiers2": []}], "All best": [{"sentence": "NV", "modifiers0": [], "subject": ["All"], "modifiers1": [], "relation": ["best"], "object": [], "modifiers2": []}], "IT Help Desk": [{"sentence": "NVN", "modifiers0": [], "subject": ["IT"], "modifiers1": [], "relation": ["Help"], "object": ["Desk"], "modifiers2": []}], "The overall institute directory is available on website https://www.iiitd. ac.in or directory": [{"sentence": "NNNNVNANNNCN", "modifiers0": [], "subject": ["The overall institute directory"], "modifiers1": [], "relation": ["is"], "object": ["available"], "modifiers2": [{"m_rel": ["on"], "m_obj": ["website https://www.iiitd ac.in", "directory"]}]}], "The vehicles entering Campus shall do so from Gate No 1": [{"sentence": "NNANVVVANNN", "modifiers0": [], "subject": ["The vehicles"], "modifiers1": [{"m_rel": ["entering"], "m_obj": ["Campus"]}], "relation": ["shall do so from"], "object": ["Gate No 1"], "modifiers2": []}], " Any vehicle reported by Faculty or Officers or SC or Security for violation will be fined Rs 200 or - first time and second violation will result in withdrawal of car sticker for one month and entry into personal record of individual": [{"sentence": "NNAANCNCNCNANVVVNNCNN", "modifiers0": [], "subject": ["Any vehicle"], "modifiers1": [{"m_rel": ["reported by"], "m_obj": ["Faculty", "Officers", "SC", "Security"]}, {"m_rel": ["for"], "m_obj": ["violation"]}], "relation": ["will be fined"], "object": ["Rs 200", "first time"], "modifiers2": []}, {"sentence": "NNVVANANNANNCNANNAN", "modifiers0": [], "subject": ["second violation"], "modifiers1": [], "relation": ["will result in"], "object": ["withdrawal"], "modifiers2": [{"m_rel": ["of"], "m_obj": ["car sticker"]}, {"m_rel": ["for"], "m_obj": ["one month", "entry"]}, {"m_rel": ["into"], "m_obj": ["personal record"]}, {"m_rel": ["of"], "m_obj": ["individual"]}]}], " The case will be referred to disciplinary committee for subsequent violations.": [{"sentence": "NNVVVANNANN", "modifiers0": [], "subject": ["The case"], "modifiers1": [], "relation": ["will be referred to"], "object": ["disciplinary committee"], "modifiers2": [{"m_rel": ["for"], "m_obj": ["subsequent violations"]}]}], "I will help ensure that others also uphold Honour Code": [{"sentence": "NVVV", "modifiers0": [], "subject": ["I"], "modifiers1": [], "relation": ["will help ensure"], "object": [], "modifiers2": []}, {"sentence": "NVVNN", "modifiers0": [], "subject": ["others"], "modifiers1": [], "relation": ["also uphold"], "object": ["Honour Code"], "modifiers2": []}], "Students using IIIT Delhi Delhi computing and networking and IT facilities are expected to": [{"sentence": "NANNNNCNCNNVVA", "modifiers0": [], "subject": ["Students"], "modifiers1": [{"m_rel": ["using"], "m_obj": ["IIIT Delhi Delhi computing", "networking", "IT facilities"]}], "relation": ["are expected to"], "object": [], "modifiers2": []}], " Chain emails or mass emails or commercial advertising are not allowed without permission.": [{"sentence": "NNCNNCNNVNAAN", "modifiers0": [], "subject": ["Chain emails", "mass emails", "commercial advertising"], "modifiers1": [], "relation": ["are"], "object": ["not"], "modifiers2": [{"m_rel": ["allowed without"], "m_obj": ["permission"]}]}], " No food or drink is permitted in laboratories": [{"sentence": "NNCNVVAN", "modifiers0": [], "subject": ["No food", "drink"], "modifiers1": [], "relation": ["is permitted in"], "object": ["laboratories"], "modifiers2": []}], " Violations of policy will be treated as academic misconduct and misdemeanour and or indiscipline as appropriate": [{"sentence": "NANVVV", "modifiers0": [], "subject": ["Violations"], "modifiers1": [{"m_rel": ["of"], "m_obj": ["policy"]}], "relation": ["will be treated"], "object": [], "modifiers2": []}, {"sentence": "NNCNCNVN", "modifiers0": [], "subject": ["academic misconduct", "misdemeanour", "indiscipline"], "modifiers1": [], "relation": ["as"], "object": ["appropriate"], "modifiers2": []}], "The policy Where Student Leaves Institute": [{"sentence": "NNVNNN", "modifiers0": [], "subject": ["The policy"], "modifiers1": [], "relation": ["Where"], "object": ["Student Leaves Institute"], "modifiers2": []}], " All logins for Internet access (mobile and laptop and PDA etc) will be deactivated from date of leaving Institute and that is convocation day.": [{"sentence": "NNANNNCNCNVVVANAAN", "modifiers0": [], "subject": ["All logins"], "modifiers1": [{"m_rel": ["for"], "m_obj": ["Internet access mobile", "laptop", "PDA"]}], "relation": ["will be deactivated from"], "object": ["date"], "modifiers2": [{"m_rel": ["of leaving"], "m_obj": ["Institute"]}]}, {"sentence": "NVNN", "modifiers0": [], "subject": ["that"], "modifiers1": [], "relation": ["is"], "object": ["convocation day"], "modifiers2": []}], " Students of IIIT Delhi will": [{"sentence": "NANNV", "modifiers0": [], "subject": ["Students"], "modifiers1": [{"m_rel": ["of"], "m_obj": ["IIIT Delhi"]}], "relation": ["will"], "object": [], "modifiers2": []}], "Respect fellow being\u2019s privacy.": [{"sentence": "NNVNN", "modifiers0": [], "subject": ["Respect fellow"], "modifiers1": [], "relation": ["being"], "object": ["\u2019s privacy"], "modifiers2": []}], "This handbook is compilation of information from various sources like Institute\u2019s website and relevant departments and government portals and which is to best of our knowledge correct at time of printing": [{"sentence": "NNVNANANNCNNNCNNCNN", "modifiers0": [], "subject": ["This handbook"], "modifiers1": [], "relation": ["is"], "object": ["compilation"], "modifiers2": [{"m_rel": ["of"], "m_obj": ["information"]}, {"m_rel": ["from"], "m_obj": ["various sources", "Institute \u2019s website", "relevant departments", "government portals"]}]}, {"sentence": "NVNNANNNANAN", "modifiers0": [], "subject": ["which"], "modifiers1": [], "relation": ["is"], "object": ["to best"], "modifiers2": [{"m_rel": ["of"], "m_obj": ["our knowledge correct"]}, {"m_rel": ["at"], "m_obj": ["time"]}, {"m_rel": ["of"], "m_obj": ["printing"]}]}]}